meteo_spark/__init__.py
meteo_spark/dataset.py
meteo_spark-0.1.0.dist-info/LICENSE
meteo_spark-0.1.0.dist-info/METADATA
meteo_spark-0.1.0.dist-info/NOTICE
meteo_spark-0.1.0.dist-info/WHEEL
meteo_spark-0.1.0.dist-info/top_level.txt
meteo_spark-0.1.0.dist-info/RECORD
