Metadata-Version: 2.1
Name: meteo-spark
Version: 0.1.0
Summary: A python package to process climate scientific files using pyspark.
Home-page: https://github.com/hussein-awala/MeteoSpark
Author: Hussein Awala
Author-email: hussein.awala.96@gmail.com
License: http://www.apache.org/licenses/LICENSE-2.0
Project-URL: Bug Tracker, https://github.com/hussein-awala/MeteoSpark/issues
Platform: UNKNOWN
Classifier: Programming Language :: Python :: 3
Classifier: License :: OSI Approved :: Apache Software License
Classifier: Operating System :: OS Independent
Requires-Python: >=3.6
License-File: LICENSE
License-File: NOTICE
Requires-Dist: pyspark
Requires-Dist: xarray
Requires-Dist: dask
Requires-Dist: h5netcdf
Requires-Dist: fsspec
Requires-Dist: s3fs
